CHANGELOG.md
LICENSE
qats/__init__.py
qats/__main__.py
qats/_version.py
qats/app/__init__.py
qats/app/exceptions.py
qats/app/funcs.py
qats/app/gui.py
qats/app/logger.py
qats/app/qats.ico
qats/app/threading.py
qats/app/widgets.py
qats/cli.py
qats/fatigue/__init__.py
qats/fatigue/corrections.py
qats/fatigue/rainflow.py
qats/fatigue/sn.py
qats/io/__init__.py
qats/io/csv.py
qats/io/direct_access.py
qats/io/other.py
qats/io/pickle_format.py
qats/io/sima.py
qats/io/sima_h5.py
qats/io/sintef_mat.py
qats/io/tdms.py
qats/motions.py
qats/signal.py
qats/stats/__init__.py
qats/stats/empirical.py
qats/stats/gumbel.py
qats/stats/gumbelmin.py
qats/stats/weibull.py
qats/ts.py
qats/tsdb.py
qats-5.2.1.dist-info/LICENSE
qats-5.2.1.dist-info/METADATA
qats-5.2.1.dist-info/WHEEL
qats-5.2.1.dist-info/entry_points.txt
qats-5.2.1.dist-info/RECORD
