Metadata-Version: 2.1
Name: qats
Version: 5.2.1
Summary: Library for efficient processing and visualization of time series
Home-page: https://github.com/dnvgl/qats
License: MIT
Author: Per Voie
Author-email: per.voie@gmail.com
Requires-Python: >=3.8.1,<3.13
Classifier: License :: OSI Approved :: MIT License
Classifier: Programming Language :: Python :: 3
Classifier: Programming Language :: Python :: 3.9
Classifier: Programming Language :: Python :: 3.10
Classifier: Programming Language :: Python :: 3.11
Classifier: Programming Language :: Python :: 3.12
Requires-Dist: h5py (>=3.5.0)
Requires-Dist: importlib-resources
Requires-Dist: matplotlib (>=3.3.3)
Requires-Dist: nptdms (>=1.1.0)
Requires-Dist: numpy (>=1.21.6) ; python_version < "3.12"
Requires-Dist: numpy (>=1.26.0) ; python_version >= "3.12"
Requires-Dist: openpyxl (>=3.0.5)
Requires-Dist: pandas (>=1.1.4) ; python_version < "3.12"
Requires-Dist: pandas (>=2.2.0) ; python_version >= "3.12"
Requires-Dist: pymatreader (>=0.0.24)
Requires-Dist: pyside6 (>=6.6.0,<7.0.0)
Requires-Dist: pywin32 (>=306,<307) ; platform_system == "Windows"
Requires-Dist: qtpy (>=1.9.0)
Requires-Dist: scipy (>=1.11.1) ; python_version >= "3.12"
Requires-Dist: scipy (>=1.9.0) ; python_version < "3.12"
Project-URL: Changelog, https://github.com/dnvgl/qats/releases
Project-URL: Documentation, https://qats.readthedocs.io
Project-URL: Download, https://pypi.org/project/qats/
Project-URL: Issues, https://github.com/dnvgl/qats/issues
Project-URL: Repository, https://github.com/dnvgl/qats
